Metadata-Version: 2.1
Name: scrapy-spiderdocs
Version: 0.1.3
Summary: Generate spiders md documentation based on spider docstrings.
Home-page: https://github.com/nanvel/scrapy-spiderdocs
Author: Oleksandr Polieno
Author-email: polyenoom@gmail.com
License: MIT License
Project-URL: Documentation, https://github.com/nanvel/scrapy-spiderdocs
Project-URL: Source, https://github.com/nanvel/scrapy-spiderdocs
Project-URL: Tracker, https://github.com/nanvel/scrapy-spiderdocs/issues
Keywords: scrapy,spiders,documentation
Platform: OS Independent
Classifier: Framework :: Scrapy
Classifier: Environment :: Console
Classifier: Operating System :: OS Independent
Classifier: License :: OSI Approved :: MIT License
Classifier: Development Status :: 5 - Production/Stable
Classifier: Intended Audience :: Developers
Classifier: Programming Language :: Python
Classifier: Programming Language :: Python :: 3
Classifier: Programming Language :: Python :: 3.7
Classifier: Programming Language :: Python :: 3.8
Classifier: Programming Language :: Python :: 3.9
Classifier: Programming Language :: Python :: 3.10
Classifier: Programming Language :: Python :: 3.11
Classifier: Topic :: Documentation
Classifier: Topic :: Internet :: WWW/HTTP
Classifier: Topic :: Software Development :: Libraries :: Application Frameworks
Classifier: Topic :: Software Development :: Libraries :: Python Modules
Requires-Python: >=3.7
License-File: LICENSE
License-File: AUTHORS
